[
    {
        "key": "dbln",
        "value": "%7B%2261566551404418%22%3A%222efVzjDr%22%2C%22100081327026752%22%3A%22hjB2CTLw%22%7D",
        "domain": "facebook.com",
        "path": "/login/device-based/",
        "hostOnly": false,
        "creation": "2024-10-17T16:41:52.534Z",
        "lastAccessed": "2024-10-17T16:41:52.550Z"
    },
    {
        "key": "datr",
        "value": "CkAJZ7tB6C7rlKfUMYVTz_09",
        "domain": "facebook.com",
        "path": "/",
        "hostOnly": false,
        "creation": "2024-10-17T16:41:52.550Z",
        "lastAccessed": "2024-10-17T16:41:52.550Z"
    },
    {
        "key": "sb",
        "value": "CkAJZ8ahUnfAzy_OFnK-xA--",
        "domain": "facebook.com",
        "path": "/",
        "hostOnly": false,
        "creation": "2024-10-17T16:41:52.550Z",
        "lastAccessed": "2024-10-17T16:41:52.550Z"
    },
    {
        "key": "vpd",
        "value": "v1%3B632x360x2",
        "domain": "facebook.com",
        "path": "/",
        "hostOnly": false,
        "creation": "2024-10-17T16:41:52.550Z",
        "lastAccessed": "2024-10-17T16:41:52.550Z"
    },
    {
        "key": "ps_l",
        "value": "1",
        "domain": "facebook.com",
        "path": "/",
        "hostOnly": false,
        "creation": "2024-10-17T16:41:52.550Z",
        "lastAccessed": "2024-10-17T16:41:52.550Z"
    },
    {
        "key": "ps_n",
        "value": "1",
        "domain": "facebook.com",
        "path": "/",
        "hostOnly": false,
        "creation": "2024-10-17T16:41:52.550Z",
        "lastAccessed": "2024-10-17T16:41:52.550Z"
    },
    {
        "key": "wd",
        "value": "360x632",
        "domain": "facebook.com",
        "path": "/",
        "hostOnly": false,
        "creation": "2024-10-17T16:41:52.551Z",
        "lastAccessed": "2024-10-17T16:41:52.551Z"
    },
    {
        "key": "c_user",
        "value": "100081327026752",
        "domain": "facebook.com",
        "path": "/",
        "hostOnly": false,
        "creation": "2024-10-17T16:41:52.551Z",
        "lastAccessed": "2024-10-17T16:41:52.551Z"
    },
    {
        "key": "fr",
        "value": "0q8ed3DiLbkGd9550.AWXBizce616qq2wbiJ9OnmjQk4k.BnCUAK..AAA.0.0.BnET2o.AWV_wlLukdo",
        "domain": "facebook.com",
        "path": "/",
        "hostOnly": false,
        "creation": "2024-10-17T16:41:52.551Z",
        "lastAccessed": "2024-10-17T16:41:52.551Z"
    },
    {
        "key": "xs",
        "value": "2%3ArZyxeq8aofutDg%3A2%3A1729183148%3A-1%3A5146",
        "domain": "facebook.com",
        "path": "/",
        "hostOnly": false,
        "creation": "2024-10-17T16:41:52.551Z",
        "lastAccessed": "2024-10-17T16:41:52.551Z"
    },
    {
        "key": "locale",
        "value": "bn_IN",
        "domain": "facebook.com",
        "path": "/",
        "hostOnly": false,
        "creation": "2024-10-17T16:41:52.551Z",
        "lastAccessed": "2024-10-17T16:41:52.551Z"
    },
    {
        "key": "fbl_st",
        "value": "100430271%3BT%3A28819719",
        "domain": "facebook.com",
        "path": "/",
        "hostOnly": false,
        "creation": "2024-10-17T16:41:52.551Z",
        "lastAccessed": "2024-10-17T16:41:52.551Z"
    },
    {
        "key": "wl_cbv",
        "value": "v2%3Bclient_version%3A2650%3Btimestamp%3A1729183158",
        "domain": "facebook.com",
        "path": "/",
        "hostOnly": false,
        "creation": "2024-10-17T16:41:52.551Z",
        "lastAccessed": "2024-10-17T16:41:52.551Z"
    }
        ]
